{
  "courses": [
    {
      "title": "Lógica de Programação",
      "category": "Front-End",
      "date": "15/02/2021",
      "id": 1
    },
    {
      "title": "Orientação a Objetos com Java",
      "category": "Java",
      "date": "23/02/2021",
      "id": 2
    },
    {
      "title": "Introdução a Banco de Dados com SQL",
      "category": "Banco de Dados",
      "date": "03/03/2021",
      "id": 3
    },
    {
      "title": "Criando aplicativos com Android",
      "category": "Mobile",
      "date": "14/03/2021",
      "id": 4
    },
    {
      "title": "Flexbox: Posicione elementos na tela",
      "category": "Front-End",
      "date": "14/03/2021",
      "id": 5
    },
    {
      "title": "CSS",
      "category": "Front-End",
      "date": "18/05/2021",
      "id": 6
    },
    {
      "title": "StyledComponents",
      "category": "Front-End",
      "date": "18/05/2021",
      "id": 7
    }
  ]
}